xl_docx/__init__.py
xl_docx/__main__.py
xl_docx/document.py
xl_docx/h.docx
xl_docx/sheet.py
xl_docx/test.py
xl_docx/v.docx
xl_docx/word_file.py
xl_docx/compiler/__init__.py
xl_docx/compiler/processors/__init__.py
xl_docx/compiler/processors/base.py
xl_docx/compiler/processors/directive.py
xl_docx/compiler/processors/pager.py
xl_docx/compiler/processors/style.py
xl_docx/compiler/processors/table.py
xl_docx/compiler/processors/paragraph/__init__.py
xl_docx/compiler/processors/paragraph/image.py
xl_docx/components/page-break.xml
xl_docx/components/pager.xml
xl_docx/components/xl-block.xml
xl_docx/components/xl-box-image.xml
xl_docx/components/xl-check.xml
xl_docx/components/xl-page.xml
xl_docx/components/xl-repeat.xml
xl_docx/components/xl-text.xml
xl_docx/loader/__init__.py
xl_docx/mcp/__init__.py
xl_docx/mcp/word_mcp.py
xl_docx/mcp/xml_syntax_reference.txt
xl_docx/mixins/__init__.py
xl_docx/mixins/component.py
xl_docx/mixins/relation.py
xl_docx/output/doc_1.docx
xl_docx/output/doc_2.docx
xl_docx/scripts/clean_rsid_attributes.py
xl_docx/scripts/process_body_xml_files.py
xl_docx/scripts/process_ftr_xml_files.py
xl_docx/scripts/process_hdr_xml_files.py
xl_docx/utils/fake_zip.py
xl_docx/utils/tree.py
xl_docx/utils/tool/__init__.py
xl_docx/utils/tool/build.bat
xl_docx/utils/tool/document.xml
xl_docx/utils/tool/gui.py
xl_docx/utils/tool/h.docx
xl_docx/utils/tool/tool.spec
xl_docx/utils/tool/utility.py
xl_docx/utils/tool/v.docx
xl_docx-3.0.6.dist-info/METADATA
xl_docx-3.0.6.dist-info/WHEEL
xl_docx-3.0.6.dist-info/RECORD
