Metadata-Version: 2.4
Name: xl-docx
Version: 3.0.6
Summary: generate word documents in a sexy way
Project-URL: Homepage, https://github.com/xilong/py-docx
Project-URL: Bug Tracker, https://github.com/xilong/py-docx/issues
Author-email: xilong <xilong_tech@163.com>
Classifier: License :: OSI Approved :: MIT License
Classifier: Operating System :: OS Independent
Classifier: Programming Language :: Python :: 3
Requires-Python: >=3.7
Requires-Dist: cssselect==1.2.0
Requires-Dist: jinja2==3.1.2
Requires-Dist: lxml==4.9.2
Requires-Dist: openai==1.3.0
